{
    "folder":"acchen_000119",
    "objects":[
        {
            "label":"sky",
            "priority":"0",
            "size":"0.25163"
        },
        {
            "label":"building",
            "priority":"0",
            "size":"0.43346"
        },
        {
            "label":"road",
            "priority":"0",
            "size":"0.53424"
        },
        {
            "label":"parking",
            "priority":"0",
            "size":"0.00487"
        },
        {
            "label":"car",
            "priority":"0",
            "size":"0.00024"
        },
        {
            "label":"terrain",
            "priority":"0",
            "size":"0.00021"
        },
        {
            "label":"car",
            "priority":"0",
            "size":"0.00080"
        },
        {
            "label":"car",
            "priority":"0",
            "size":"0.00095"
        },
        {
            "label":"sidewalk",
            "priority":"0",
            "size":"0.00712"
        },
        {
            "label":"static",
            "priority":"0",
            "size":"0.00037"
        },
        {
            "label":"car",
            "priority":"0",
            "size":"0.00023"
        },
        {
            "label":"car",
            "priority":"0",
            "size":"0.00040"
        },
        {
            "label":"static",
            "priority":"0",
            "size":"0.00157"
        },
        {
            "label":"car",
            "priority":"0",
            "size":"0.00051"
        },
        {
            "label":"car",
            "priority":"0",
            "size":"0.00063"
        },
        {
            "label":"static",
            "priority":"0",
            "size":"0.00063"
        },
        {
            "label":"car",
            "priority":"0",
            "size":"0.00198"
        },
        {
            "label":"car",
            "priority":"0",
            "size":"0.00115"
        },
        {
            "label":"vegetation",
            "priority":"0",
            "size":"0.08049"
        },
        {
            "label":"pole",
            "priority":"0",
            "size":"0.00028"
        },
        {
            "label":"car",
            "priority":"0",
            "size":"0.00029"
        },
        {
            "label":"car",
            "priority":"0",
            "size":"0.00064"
        },
        {
            "label":"terrain",
            "priority":"0",
            "size":"0.00004"
        },
        {
            "label":"pole",
            "priority":"0",
            "size":"0.00014"
        },
        {
            "label":"terrain",
            "priority":"0",
            "size":"0.00006"
        },
        {
            "label":"terrain",
            "priority":"0",
            "size":"0.00012"
        },
        {
            "label":"car",
            "priority":"0",
            "size":"0.00120"
        },
        {
            "label":"car",
            "priority":"0",
            "size":"0.00104"
        },
        {
            "label":"car",
            "priority":"0",
            "size":"0.00466"
        },
        {
            "label":"static",
            "priority":"0",
            "size":"0.00750"
        },
        {
            "label":"terrain",
            "priority":"0",
            "size":"0.00069"
        },
        {
            "label":"pole",
            "priority":"0",
            "size":"0.00131"
        },
        {
            "label":"traffic sign",
            "priority":"0",
            "size":"0.00016"
        },
        {
            "label":"vegetation",
            "priority":"0",
            "size":"0.00248"
        },
        {
            "label":"bicycle",
            "priority":"0",
            "size":"0.00107"
        },
        {
            "label":"static",
            "priority":"0",
            "size":"0.00039"
        },
        {
            "label":"static",
            "priority":"0",
            "size":"0.00039"
        },
        {
            "label":"pole",
            "priority":"0",
            "size":"0.00069"
        },
        {
            "label":"car",
            "priority":"0",
            "size":"0.00026"
        },
        {
            "label":"vegetation",
            "priority":"0",
            "size":"0.00031"
        },
        {
            "label":"vegetation",
            "priority":"0",
            "size":"0.07410"
        },
        {
            "label":"sidewalk",
            "priority":"0",
            "size":"0.01021"
        },
        {
            "label":"pole",
            "priority":"0",
            "size":"0.00054"
        },
        {
            "label":"bicycle",
            "priority":"0",
            "size":"0.00100"
        },
        {
            "label":"rider",
            "priority":"0",
            "size":"0.00178"
        },
        {
            "label":"pole",
            "priority":"0",
            "size":"0.00023"
        },
        {
            "label":"pole",
            "priority":"0",
            "size":"0.00091"
        },
        {
            "label":"traffic sign",
            "priority":"0",
            "size":"0.00013"
        },
        {
            "label":"pole",
            "priority":"0",
            "size":"0.00067"
        },
        {
            "label":"car",
            "priority":"0",
            "size":"0.00195"
        },
        {
            "label":"person",
            "priority":"0",
            "size":"0.00100"
        },
        {
            "label":"traffic light",
            "priority":"0",
            "size":"0.00112"
        },
        {
            "label":"bridge",
            "priority":"0",
            "size":"0.00015"
        },
        {
            "label":"pole",
            "priority":"0",
            "size":"0.00004"
        },
        {
            "label":"traffic sign",
            "priority":"0",
            "size":"0.00023"
        },
        {
            "label":"static",
            "priority":"0",
            "size":"0.00079"
        },
        {
            "label":"pole",
            "priority":"0",
            "size":"0.00054"
        },
        {
            "label":"car",
            "priority":"0",
            "size":"0.00563"
        },
        {
            "label":"traffic light",
            "priority":"0",
            "size":"0.00020"
        },
        {
            "label":"traffic sign",
            "priority":"0",
            "size":"0.00018"
        },
        {
            "label":"pole",
            "priority":"0",
            "size":"0.00034"
        },
        {
            "label":"car",
            "priority":"0",
            "size":"0.03136"
        },
        {
            "label":"person",
            "priority":"0",
            "size":"0.00111"
        },
        {
            "label":"static",
            "priority":"0",
            "size":"0.00424"
        },
        {
            "label":"person",
            "priority":"0",
            "size":"0.00057"
        },
        {
            "label":"pole",
            "priority":"0",
            "size":"0.00050"
        },
        {
            "label":"traffic sign",
            "priority":"0",
            "size":"0.00003"
        },
        {
            "label":"traffic sign",
            "priority":"0",
            "size":"0.00022"
        },
        {
            "label":"traffic light",
            "priority":"0",
            "size":"0.00109"
        },
        {
            "label":"pole",
            "priority":"0",
            "size":"0.00111"
        },
        {
            "label":"pole",
            "priority":"0",
            "size":"0.00046"
        },
        {
            "label":"static",
            "priority":"0",
            "size":"0.00113"
        },
        {
            "label":"static",
            "priority":"0",
            "size":"0.00021"
        },
        {
            "label":"license plate",
            "priority":"0",
            "size":"0.00107"
        },
        {
            "label":"pole",
            "priority":"0",
            "size":"0.00055"
        },
        {
            "label":"traffic light",
            "priority":"0",
            "size":"0.00172"
        },
        {
            "label":"pole",
            "priority":"0",
            "size":"0.00269"
        },
        {
            "label":"traffic light",
            "priority":"0",
            "size":"0.00051"
        },
        {
            "label":"traffic sign",
            "priority":"0",
            "size":"0.00064"
        },
        {
            "label":"traffic light",
            "priority":"0",
            "size":"0.00223"
        },
        {
            "label":"pole",
            "priority":"0",
            "size":"0.00053"
        },
        {
            "label":"traffic light",
            "priority":"0",
            "size":"0.00118"
        },
        {
            "label":"traffic light",
            "priority":"0",
            "size":"0.00141"
        },
        {
            "label":"person",
            "priority":"0",
            "size":"0.00074"
        },
        {
            "label":"car",
            "priority":"0",
            "size":"0.07553"
        },
        {
            "label":"license plate",
            "priority":"0",
            "size":"0.00284"
        },
        {
            "label":"pole",
            "priority":"0",
            "size":"0.00012"
        },
        {
            "label":"license plate",
            "priority":"0",
            "size":"0.00009"
        },
        {
            "label":"traffic light",
            "priority":"0",
            "size":"0.00031"
        },
        {
            "label":"pole",
            "priority":"0",
            "size":"0.00010"
        },
        {
            "label":"traffic light",
            "priority":"0",
            "size":"0.00027"
        },
        {
            "label":"pole",
            "priority":"0",
            "size":"0.00021"
        },
        {
            "label":"static",
            "priority":"0",
            "size":"0.00010"
        },
        {
            "label":"static",
            "priority":"0",
            "size":"0.00055"
        },
        {
            "label":"static",
            "priority":"0",
            "size":"0.00028"
        },
        {
            "label":"static",
            "priority":"0",
            "size":"0.00003"
        },
        {
            "label":"ego vehicle",
            "priority":"0",
            "size":"0.04209"
        },
        {
            "label":"out of roi",
            "priority":"0",
            "size":"0.01460"
        }
    ]
}