{
    "folder":"acchen_000000",
    "objects":[
        {
            "label":"road",
            "priority":"0",
            "size":"0.51256"
        },
        {
            "label":"sidewalk",
            "priority":"0",
            "size":"0.00262"
        },
        {
            "label":"car",
            "priority":"0",
            "size":"0.00823"
        },
        {
            "label":"car",
            "priority":"0",
            "size":"0.00412"
        },
        {
            "label":"car",
            "priority":"0",
            "size":"0.00449"
        },
        {
            "label":"sky",
            "priority":"0",
            "size":"0.15910"
        },
        {
            "label":"terrain",
            "priority":"0",
            "size":"0.01279"
        },
        {
            "label":"building",
            "priority":"0",
            "size":"0.36511"
        },
        {
            "label":"building",
            "priority":"0",
            "size":"0.04568"
        },
        {
            "label":"car",
            "priority":"0",
            "size":"0.00120"
        },
        {
            "label":"terrain",
            "priority":"0",
            "size":"0.02780"
        },
        {
            "label":"terrain",
            "priority":"0",
            "size":"0.03834"
        },
        {
            "label":"sidewalk",
            "priority":"0",
            "size":"0.02039"
        },
        {
            "label":"car",
            "priority":"0",
            "size":"0.00229"
        },
        {
            "label":"vegetation",
            "priority":"0",
            "size":"0.00689"
        },
        {
            "label":"car",
            "priority":"0",
            "size":"0.00308"
        },
        {
            "label":"pole",
            "priority":"0",
            "size":"0.00014"
        },
        {
            "label":"pole",
            "priority":"0",
            "size":"0.00015"
        },
        {
            "label":"pole",
            "priority":"0",
            "size":"0.00014"
        },
        {
            "label":"pole",
            "priority":"0",
            "size":"0.00056"
        },
        {
            "label":"car",
            "priority":"0",
            "size":"0.00035"
        },
        {
            "label":"traffic sign",
            "priority":"0",
            "size":"0.00017"
        },
        {
            "label":"car",
            "priority":"0",
            "size":"0.00084"
        },
        {
            "label":"pole",
            "priority":"0",
            "size":"0.00077"
        },
        {
            "label":"static",
            "priority":"0",
            "size":"0.00331"
        },
        {
            "label":"pole",
            "priority":"0",
            "size":"0.00084"
        },
        {
            "label":"car",
            "priority":"0",
            "size":"0.00284"
        },
        {
            "label":"pole",
            "priority":"0",
            "size":"0.00019"
        },
        {
            "label":"vegetation",
            "priority":"0",
            "size":"0.02102"
        },
        {
            "label":"pole",
            "priority":"0",
            "size":"0.00114"
        },
        {
            "label":"pole",
            "priority":"0",
            "size":"0.00050"
        },
        {
            "label":"vegetation",
            "priority":"0",
            "size":"0.07941"
        },
        {
            "label":"pole",
            "priority":"0",
            "size":"0.00037"
        },
        {
            "label":"pole",
            "priority":"0",
            "size":"0.00048"
        },
        {
            "label":"traffic sign",
            "priority":"0",
            "size":"0.00018"
        },
        {
            "label":"pole",
            "priority":"0",
            "size":"0.00016"
        },
        {
            "label":"car",
            "priority":"0",
            "size":"0.00449"
        },
        {
            "label":"static",
            "priority":"0",
            "size":"0.00009"
        },
        {
            "label":"static",
            "priority":"0",
            "size":"0.00009"
        },
        {
            "label":"pole",
            "priority":"0",
            "size":"0.00015"
        },
        {
            "label":"traffic sign",
            "priority":"0",
            "size":"0.00405"
        },
        {
            "label":"traffic sign",
            "priority":"0",
            "size":"0.00405"
        },
        {
            "label":"traffic sign",
            "priority":"0",
            "size":"0.00389"
        },
        {
            "label":"static",
            "priority":"0",
            "size":"0.00106"
        },
        {
            "label":"vegetation",
            "priority":"0",
            "size":"0.00159"
        },
        {
            "label":"static",
            "priority":"0",
            "size":"0.00070"
        },
        {
            "label":"vegetation",
            "priority":"0",
            "size":"0.00070"
        },
        {
            "label":"bicycle",
            "priority":"0",
            "size":"0.00051"
        },
        {
            "label":"person",
            "priority":"0",
            "size":"0.00039"
        },
        {
            "label":"traffic sign",
            "priority":"0",
            "size":"0.00067"
        },
        {
            "label":"pole",
            "priority":"0",
            "size":"0.00108"
        },
        {
            "label":"pole",
            "priority":"0",
            "size":"0.00040"
        },
        {
            "label":"person",
            "priority":"0",
            "size":"0.00048"
        },
        {
            "label":"car",
            "priority":"0",
            "size":"0.00823"
        },
        {
            "label":"traffic sign",
            "priority":"0",
            "size":"0.00665"
        },
        {
            "label":"pole",
            "priority":"0",
            "size":"0.00291"
        },
        {
            "label":"pole",
            "priority":"0",
            "size":"0.00279"
        },
        {
            "label":"license plate",
            "priority":"0",
            "size":"0.00015"
        },
        {
            "label":"terrain",
            "priority":"0",
            "size":"0.00075"
        },
        {
            "label":"rider",
            "priority":"0",
            "size":"0.00142"
        },
        {
            "label":"license plate",
            "priority":"0",
            "size":"0.00006"
        },
        {
            "label":"pole",
            "priority":"0",
            "size":"0.00002"
        },
        {
            "label":"traffic sign",
            "priority":"0",
            "size":"0.00015"
        },
        {
            "label":"traffic sign",
            "priority":"0",
            "size":"0.00015"
        },
        {
            "label":"traffic sign",
            "priority":"0",
            "size":"0.00388"
        },
        {
            "label":"bicycle",
            "priority":"0",
            "size":"0.00066"
        },
        {
            "label":"pole",
            "priority":"0",
            "size":"0.00077"
        },
        {
            "label":"traffic sign",
            "priority":"0",
            "size":"0.00063"
        },
        {
            "label":"static",
            "priority":"0",
            "size":"0.00016"
        },
        {
            "label":"pole",
            "priority":"0",
            "size":"0.00006"
        },
        {
            "label":"license plate",
            "priority":"0",
            "size":"0.00002"
        },
        {
            "label":"static",
            "priority":"0",
            "size":"0.00030"
        },
        {
            "label":"static",
            "priority":"0",
            "size":"0.00066"
        },
        {
            "label":"static",
            "priority":"0",
            "size":"0.00062"
        },
        {
            "label":"static",
            "priority":"0",
            "size":"0.00041"
        },
        {
            "label":"static",
            "priority":"0",
            "size":"0.00039"
        },
        {
            "label":"static",
            "priority":"0",
            "size":"0.00027"
        },
        {
            "label":"static",
            "priority":"0",
            "size":"0.00040"
        },
        {
            "label":"ego vehicle",
            "priority":"0",
            "size":"0.04209"
        },
        {
            "label":"out of roi",
            "priority":"0",
            "size":"0.01460"
        }
    ]
}